{
	"info": {
		"_postman_id": "28df8755-45ce-3cf5-bc11-e8c88862721a",
		"name": "BLiP",
		"schema": "https://schema.getpostman.com/json/collection/v2.1.0/collection.json"
	},
	"item": [
		{
			"name": "Extensions",
			"item": [
				{
					"name": "ArtificialIntelligence",
					"item": [
						{
							"name": "Create an intent",
							"request": {
								"method": "POST",
								"header": [
									{
										"key": "Authorization",
										"value": "{{Authorization}}",
										"type": "text"
									},
									{
										"key": "Content-Type",
										"value": "application/json",
										"type": "text"
									}
								],
								"body": {
									"mode": "raw",
									"raw": "{\r\n  \"id\": \"{{$guid}}\",\r\n  \"to\": \"postmaster@ai.msging.net\",\r\n  \"method\": \"set\",\r\n  \"uri\": \"/intentions\",\r\n  \"type\": \"application/vnd.iris.ai.intention+json\",\r\n  \"resource\": {\r\n      \"name\": \"Order pizza\"\r\n  }\r\n}"
								},
								"url": {
									"raw": "https://msging.net/commands",
									"protocol": "https",
									"host": [
										"msging",
										"net"
									],
									"path": [
										"commands"
									]
								}
							},
							"response": []
						},
						{
							"name": "Query the first 10 intents",
							"request": {
								"method": "POST",
								"header": [
									{
										"key": "Authorization",
										"value": "{{Authorization}}",
										"type": "text"
									},
									{
										"key": "Content-Type",
										"value": "application/json",
										"type": "text"
									}
								],
								"body": {
									"mode": "raw",
									"raw": "{\r\n  \"id\": \"{{$guid}}\",\r\n  \"to\": \"postmaster@ai.msging.net\",\r\n  \"method\": \"get\",\r\n  \"uri\": \"/intentions?$skip=0&$take=10\"\r\n}\r\n"
								},
								"url": {
									"raw": "https://msging.net/commands",
									"protocol": "https",
									"host": [
										"msging",
										"net"
									],
									"path": [
										"commands"
									]
								}
							},
							"response": []
						},
						{
							"name": "Add a question into an intent",
							"request": {
								"method": "POST",
								"header": [
									{
										"key": "Authorization",
										"value": "{{Authorization}}",
										"type": "text"
									},
									{
										"key": "Content-Type",
										"value": "application/json",
										"type": "text"
									}
								],
								"body": {
									"mode": "raw",
									"raw": "{\r\n  \"id\": \"{{$guid}}\",\r\n  \"to\": \"postmaster@ai.msging.net\",\r\n  \"method\": \"set\",\r\n  \"uri\": \"/intentions/order_pizza/questions\",\r\n  \"type\": \"application/vnd.lime.collection+json\",\r\n  \"resource\": {\r\n    \"itemType\": \"application/vnd.iris.ai.question+json\",\r\n    \"items\":[\r\n      {\r\n        \"text\": \"I want a pizza\"\r\n      },\r\n      {\r\n        \"text\": \"I wanna order a pizza\"\r\n      },\r\n      {\r\n        \"text\": \"Give me a pizza\"\r\n      }\r\n    ]\r\n  }\r\n}"
								},
								"url": {
									"raw": "https://msging.net/commands",
									"protocol": "https",
									"host": [
										"msging",
										"net"
									],
									"path": [
										"commands"
									]
								}
							},
							"response": []
						},
						{
							"name": "Create an entity",
							"request": {
								"method": "POST",
								"header": [
									{
										"key": "Authorization",
										"value": "{{Authorization}}",
										"type": "text"
									},
									{
										"key": "Content-Type",
										"value": "application/json",
										"type": "text"
									}
								],
								"body": {
									"mode": "raw",
									"raw": "{\r\n  \"id\":\"{{$guid}}\",\r\n  \"to\":\"postmaster@ai.msging.net\",\r\n  \"method\":\"set\",\r\n  \"uri\":\"/entities\",\r\n  \"type\":\"application/vnd.iris.ai.entity+json\",\r\n  \"resource\":{\r\n    \"name\":\"Flavor\",\r\n    \"values\":[\r\n      {\r\n        \"name\":\"Pepperoni\",\r\n        \"synonymous\":[\r\n          \"Peperoni\",\r\n          \"Pepperonee\",\r\n          \"Pepperouni\",\r\n          \"Peperony\"\r\n        ]\r\n      },\r\n      {\r\n        \"name\":\"Mushrooms\",\r\n        \"synonymous\":[\r\n          \"Mashrooms\",\r\n          \"Mushroom\",\r\n          \"Mshrooms\"\r\n        ]\r\n      }\r\n    ]\r\n  }\r\n}"
								},
								"url": {
									"raw": "https://msging.net/commands",
									"protocol": "https",
									"host": [
										"msging",
										"net"
									],
									"path": [
										"commands"
									]
								}
							},
							"response": []
						},
						{
							"name": "Associate answers to an intent",
							"request": {
								"method": "POST",
								"header": [
									{
										"key": "Authorization",
										"value": "{{Authorization}}",
										"type": "text"
									},
									{
										"key": "Content-Type",
										"value": "application/json",
										"type": "text"
									}
								],
								"body": {
									"mode": "raw",
									"raw": "{\r\n  \"id\": \"{{$guid}}\",\r\n  \"to\": \"postmaster@ai.msging.net\",\r\n  \"method\": \"set\",\r\n  \"uri\": \"/intentions/order_pizza/answers\",\r\n  \"type\": \"application/vnd.lime.collection+json\",\r\n  \"resource\": {\r\n    \"itemType\": \"application/vnd.iris.ai.answer+json\",\r\n    \"items\":[\r\n      {\r\n        \"type\":\"text/plain\",\r\n        \"value\":\"Which flavor do you want?\"\r\n      }\r\n    ]\r\n  }\r\n}"
								},
								"url": {
									"raw": "https://msging.net/commands",
									"protocol": "https",
									"host": [
										"msging",
										"net"
									],
									"path": [
										"commands"
									]
								}
							},
							"response": []
						},
						{
							"name": "Train model",
							"request": {
								"method": "POST",
								"header": [
									{
										"key": "Authorization",
										"value": "{{Authorization}}",
										"type": "text"
									},
									{
										"key": "Content-Type",
										"value": "application/json",
										"type": "text"
									}
								],
								"body": {
									"mode": "raw",
									"raw": "{\r\n  \"id\": \"{{$guid}}\",\r\n  \"to\": \"postmaster@ai.msging.net\",\r\n  \"method\": \"set\",\r\n  \"uri\": \"/models\",\r\n  \"type\": \"application/vnd.iris.ai.model-training+json\",\r\n  \"resource\": {\r\n  }\r\n}"
								},
								"url": {
									"raw": "https://msging.net/commands",
									"protocol": "https",
									"host": [
										"msging",
										"net"
									],
									"path": [
										"commands"
									]
								}
							},
							"response": []
						},
						{
							"name": "Query trained models",
							"request": {
								"method": "POST",
								"header": [
									{
										"key": "Authorization",
										"value": "{{Authorization}}",
										"type": "text"
									},
									{
										"key": "Content-Type",
										"name": "Content-Type",
										"value": "application/json",
										"type": "text"
									}
								],
								"body": {
									"mode": "raw",
									"raw": "{\r\n  \"id\": \"{{$guid}}\",\r\n  \"to\": \"postmaster@ai.msging.net\",\r\n  \"method\": \"get\",\r\n  \"uri\": \"/models\"\r\n}"
								},
								"url": {
									"raw": "https://msging.net/commands",
									"protocol": "https",
									"host": [
										"msging",
										"net"
									],
									"path": [
										"commands"
									]
								}
							},
							"response": []
						},
						{
							"name": "Publish a trained model",
							"request": {
								"method": "POST",
								"header": [
									{
										"key": "Authorization",
										"value": "{{Authorization}}",
										"type": "text"
									},
									{
										"key": "Content-Type",
										"name": "Content-Type",
										"value": "application/json",
										"type": "text"
									}
								],
								"body": {
									"mode": "raw",
									"raw": "{\r\n  \"id\": \"{{$guid}}\",\r\n  \"to\": \"postmaster@ai.msging.net\",\r\n  \"method\": \"set\",\r\n  \"uri\": \"/models\",\r\n  \"type\": \"application/vnd.iris.ai.model-publishing+json\",\r\n  \"resource\": {\r\n    \"id\":\"{{your-model-id}}\"\r\n  }\r\n}"
								},
								"url": {
									"raw": "https://msging.net/commands",
									"protocol": "https",
									"host": [
										"msging",
										"net"
									],
									"path": [
										"commands"
									]
								}
							},
							"response": []
						},
						{
							"name": "Analyze a sentence",
							"request": {
								"method": "POST",
								"header": [
									{
										"key": "Authorization",
										"value": "{{Authorization}}",
										"type": "text"
									},
									{
										"key": "Content-Type",
										"value": "application/json",
										"type": "text"
									}
								],
								"body": {
									"mode": "raw",
									"raw": "{\r\n  \"id\": \"{{$guid}}\",\r\n  \"to\": \"postmaster@ai.msging.net\",\r\n  \"method\": \"set\",\r\n  \"uri\": \"/analysis\",\r\n  \"type\": \"application/vnd.iris.ai.analysis-request+json\",\r\n  \"resource\": {\r\n    \"text\":\"I want a pepperoni pizza\"\r\n  }\r\n}"
								},
								"url": {
									"raw": "https://msging.net/commands",
									"protocol": "https",
									"host": [
										"msging",
										"net"
									],
									"path": [
										"commands"
									]
								}
							},
							"response": []
						},
						{
							"name": "Analyze a sentence for a specific model",
							"request": {
								"method": "POST",
								"header": [
									{
										"key": "Authorization",
										"value": "{{Authorization}}",
										"type": "text"
									},
									{
										"key": "Content-Type",
										"value": "application/json",
										"type": "text"
									}
								],
								"body": {
									"mode": "raw",
									"raw": "{\r\n  \"id\": \"{{$guid}}\",\r\n  \"to\": \"postmaster@ai.msging.net\",\r\n  \"method\": \"set\",\r\n  \"uri\": \"/analysis\",\r\n  \"type\": \"application/vnd.iris.ai.analysis-request+json\",\r\n  \"resource\": {\r\n    \"text\":\"I want a pepperoni pizza\",\r\n    \"modelId\":\"{{your-model-id}}\"\r\n  }\r\n}"
								},
								"url": {
									"raw": "https://msging.net/commands",
									"protocol": "https",
									"host": [
										"msging",
										"net"
									],
									"path": [
										"commands"
									]
								}
							},
							"response": []
						},
						{
							"name": "Get the last analysis",
							"request": {
								"method": "POST",
								"header": [
									{
										"key": "Authorization",
										"value": "{{Authorization}}",
										"type": "text"
									},
									{
										"key": "Content-Type",
										"value": "application/json",
										"type": "text"
									}
								],
								"body": {
									"mode": "raw",
									"raw": "{\r\n  \"id\": \"{{$guid}}}\",\r\n  \"to\": \"postmaster@ai.msging.net\",\r\n  \"method\": \"get\",\r\n  \"uri\": \"/analysis?$take=10&$filter=feedback%20eq%20none\"\r\n}"
								},
								"url": {
									"raw": "https://msging.net/commands",
									"protocol": "https",
									"host": [
										"msging",
										"net"
									],
									"path": [
										"commands"
									]
								}
							},
							"response": []
						},
						{
							"name": "Send an 'approved' enhancement",
							"request": {
								"method": "POST",
								"header": [
									{
										"key": "Authorization",
										"value": "{{Authorization}}",
										"type": "text"
									},
									{
										"key": "Content-Type",
										"value": "application/json",
										"type": "text"
									}
								],
								"body": {
									"mode": "raw",
									"raw": "{\r\n  \"id\":\"{{$guid}}\",\r\n  \"to\":\"postmaster@ai.msging.net\",\r\n  \"method\":\"set\",\r\n  \"uri\":\"/analysis/{{analyse-id}}/feedback\",\r\n  \"type\":\"application/vnd.iris.ai.analysis-feedback+json\",\r\n  \"resource\":{\r\n    \"feedback\":\"approved\"\r\n  }\r\n}"
								},
								"url": {
									"raw": "https://msging.net/commands",
									"protocol": "https",
									"host": [
										"msging",
										"net"
									],
									"path": [
										"commands"
									]
								}
							},
							"response": []
						},
						{
							"name": "Send an 'rejected' enhancement",
							"request": {
								"method": "POST",
								"header": [
									{
										"key": "Authorization",
										"type": "text",
										"value": "{{Authorization}}"
									},
									{
										"key": "Content-Type",
										"type": "text",
										"value": "application/json"
									}
								],
								"body": {
									"mode": "raw",
									"raw": "{\r\n  \"id\":\"{{$guid}}\",\r\n  \"to\":\"postmaster@ai.msging.net\",\r\n  \"method\":\"set\",\r\n  \"uri\":\"/analysis/{{analyse-id}}/feedback\",\r\n  \"type\":\"application/vnd.iris.ai.analysis-feedback+json\",\r\n  \"resource\":{\r\n    \"feedback\":\"rejected\",\r\n    \"intentionId\":\"{{other_intention_id}}\"\r\n  }\r\n}"
								},
								"url": {
									"raw": "https://msging.net/commands",
									"protocol": "https",
									"host": [
										"msging",
										"net"
									],
									"path": [
										"commands"
									]
								}
							},
							"response": []
						},
						{
							"name": "Delete an intent",
							"request": {
								"method": "POST",
								"header": [
									{
										"key": "Authorization",
										"value": "{{Authorization}}",
										"type": "text"
									},
									{
										"key": "Content-Type",
										"name": "Content-Type",
										"value": "application/json",
										"type": "text"
									}
								],
								"body": {
									"mode": "raw",
									"raw": "{\r\n  \"id\": \"{{$guid}}\",\r\n  \"to\": \"postmaster@ai.msging.net\",\r\n  \"method\": \"delete\",\r\n  \"uri\": \"/intentions/order_pizza\"\r\n}"
								},
								"url": {
									"raw": "https://msging.net/commands",
									"protocol": "https",
									"host": [
										"msging",
										"net"
									],
									"path": [
										"commands"
									]
								}
							},
							"response": []
						}
					],
					"description": "All requests for Artificial Intelligence extension",
					"_postman_isSubFolder": true
				},
				{
					"name": "Broadcast",
					"item": [
						{
							"name": "Create a list",
							"request": {
								"method": "POST",
								"header": [
									{
										"key": "Authorization",
										"value": "{{Authorization}}",
										"type": "text"
									},
									{
										"key": "Content-Type",
										"value": "application/json",
										"type": "text"
									}
								],
								"body": {
									"mode": "raw",
									"raw": "{  \r\n  \"id\": \"{{$guid}}\",\r\n  \"to\": \"postmaster@broadcast.msging.net\",\r\n  \"method\": \"set\",\r\n  \"type\": \"application/vnd.iris.distribution-list+json\",\r\n  \"uri\": \"/lists\",\r\n  \"resource\": {  \r\n    \"identity\": \"{{your_distribution_list_name}}@broadcast.msging.net\"\r\n  }\r\n}"
								},
								"url": {
									"raw": "https://msging.net/commands",
									"protocol": "https",
									"host": [
										"msging",
										"net"
									],
									"path": [
										"commands"
									]
								}
							},
							"response": []
						},
						{
							"name": "Get lists",
							"request": {
								"method": "POST",
								"header": [
									{
										"key": "Authorization",
										"type": "text",
										"value": "{{Authorization}}"
									},
									{
										"key": "Content-Type",
										"type": "text",
										"value": "application/json"
									}
								],
								"body": {
									"mode": "raw",
									"raw": "{  \r\n  \"id\": \"{{$guid}}\",\r\n  \"to\": \"postmaster@broadcast.msging.net\",\r\n  \"method\": \"get\",\r\n  \"uri\": \"/lists\"\r\n}"
								},
								"url": {
									"raw": "https://msging.net/commands",
									"protocol": "https",
									"host": [
										"msging",
										"net"
									],
									"path": [
										"commands"
									]
								}
							},
							"response": []
						},
						{
							"name": "Add a member to a list",
							"request": {
								"method": "POST",
								"header": [
									{
										"key": "Authorization",
										"type": "text",
										"value": "{{Authorization}}"
									},
									{
										"key": "Content-Type",
										"type": "text",
										"value": "application/json"
									}
								],
								"body": {
									"mode": "raw",
									"raw": "{  \r\n  \"id\": \"{{$guid}}\",\r\n  \"to\": \"postmaster@broadcast.msging.net\",\r\n  \"method\": \"set\",\r\n  \"uri\": \"/lists/{{your_distribution_list_name}}@broadcast.msging.net/recipients\",\r\n  \"type\": \"application/vnd.lime.identity\",\r\n  \"resource\": \"{{userIdentity}}\"\r\n}"
								},
								"url": {
									"raw": "https://msging.net/commands",
									"protocol": "https",
									"host": [
										"msging",
										"net"
									],
									"path": [
										"commands"
									]
								}
							},
							"response": []
						},
						{
							"name": "Remove members from a list",
							"request": {
								"method": "POST",
								"header": [
									{
										"key": "Authorization",
										"type": "text",
										"value": "{{Authorization}}"
									},
									{
										"key": "Content-Type",
										"type": "text",
										"value": "application/json"
									}
								],
								"body": {
									"mode": "raw",
									"raw": "{  \r\n  \"id\": \"{{$guid}}\",\r\n  \"to\": \"postmaster@broadcast.msging.net\",\r\n  \"method\": \"delete\",\r\n  \"uri\": \"/lists/{{your-distribution-list-name}}@broadcast.msging.net/recipients/{{member-identity}}\"\r\n}"
								},
								"url": {
									"raw": "https://msging.net/commands",
									"protocol": "https",
									"host": [
										"msging",
										"net"
									],
									"path": [
										"commands"
									]
								}
							},
							"response": []
						},
						{
							"name": "Get all members of a list",
							"request": {
								"method": "POST",
								"header": [
									{
										"key": "Authorization",
										"type": "text",
										"value": "{{Authorization}}"
									},
									{
										"key": "Content-Type",
										"type": "text",
										"value": "application/json"
									}
								],
								"body": {
									"mode": "raw",
									"raw": "{  \r\n  \"id\": \"{{$guid}}\",\r\n  \"to\": \"postmaster@broadcast.msging.net\",\r\n  \"method\": \"get\",\r\n  \"uri\": \"/lists/{{your_distribution-list-name}}@broadcast.msging.net/recipients?$skip=0&$take=5\"\r\n}"
								},
								"url": {
									"raw": "https://msging.net/commands",
									"protocol": "https",
									"host": [
										"msging",
										"net"
									],
									"path": [
										"commands"
									]
								}
							},
							"response": []
						},
						{
							"name": "Send message to a list",
							"request": {
								"method": "POST",
								"header": [
									{
										"key": "Authorization",
										"value": "{{Authorization}}",
										"type": "text"
									},
									{
										"key": "Content-Type",
										"name": "Content-Type",
										"value": "application/json",
										"type": "text"
									}
								],
								"body": {
									"mode": "raw",
									"raw": "{  \r\n  \"id\": \"{{$guid}}\",\r\n  \"to\": \"your_distribution-list-name@broadcast.msging.net\",\r\n  \"type\": \"text/plain\",\r\n  \"content\": \"Hello participants of this list!\"\r\n}"
								},
								"url": {
									"raw": "https://msging.net/commands",
									"protocol": "https",
									"host": [
										"msging",
										"net"
									],
									"path": [
										"commands"
									]
								}
							},
							"response": []
						}
					],
					"_postman_isSubFolder": true
				},
				{
					"name": "Bucket",
					"item": [
						{
							"name": "Store a document",
							"request": {
								"method": "POST",
								"header": [
									{
										"key": "Authorization",
										"type": "text",
										"value": "{{Authorization}}"
									},
									{
										"key": "Content-Type",
										"type": "text",
										"value": "application/json"
									}
								],
								"body": {
									"mode": "raw",
									"raw": "{  \r\n  \"id\": \"{{$guid}}\",\r\n  \"method\": \"set\",\r\n  \"uri\": \"/buckets/{{your-document-key}}\",\r\n  \"type\": \"application/json\",\r\n  \"resource\": {  \r\n    \"key1\": \"value1\",\r\n    \"key2\": 2,\r\n    \"key3\": [  \r\n      \"3a\", \"3b\", \"3c\"\r\n    ]\r\n  }\r\n}"
								},
								"url": {
									"raw": "https://msging.net/commands",
									"protocol": "https",
									"host": [
										"msging",
										"net"
									],
									"path": [
										"commands"
									]
								}
							},
							"response": []
						},
						{
							"name": "Get a document",
							"request": {
								"method": "POST",
								"header": [
									{
										"key": "Authorization",
										"type": "text",
										"value": "{{Authorization}}"
									},
									{
										"key": "Content-Type",
										"type": "text",
										"value": "application/json"
									}
								],
								"body": {
									"mode": "raw",
									"raw": "{  \r\n  \"id\": \"3\",\r\n  \"method\": \"get\",\r\n  \"uri\": \"/buckets/{{your-document-key}}\"\r\n}"
								},
								"url": {
									"raw": "https://msging.net/commands",
									"protocol": "https",
									"host": [
										"msging",
										"net"
									],
									"path": [
										"commands"
									]
								}
							},
							"response": []
						}
					],
					"_postman_isSubFolder": true
				},
				{
					"name": "ChatHistory",
					"item": [
						{
							"name": "Get Last Threads",
							"request": {
								"method": "POST",
								"header": [
									{
										"key": "Authorization",
										"value": "{{Authorization}}",
										"type": "text"
									},
									{
										"key": "Content-Type",
										"name": "Content-Type",
										"value": "application/json",
										"type": "text"
									}
								],
								"body": {
									"mode": "raw",
									"raw": "{  \r\n  \"id\": \"{{$guid}}\",\r\n  \"method\": \"get\",\r\n  \"uri\": \"/threads\"\r\n}"
								},
								"url": {
									"raw": "https://msging.net/commands",
									"protocol": "https",
									"host": [
										"msging",
										"net"
									],
									"path": [
										"commands"
									]
								}
							},
							"response": []
						},
						{
							"name": "Get Last Messages",
							"request": {
								"method": "POST",
								"header": [
									{
										"key": "Authorization",
										"value": "{{Authorization}}",
										"type": "text"
									},
									{
										"key": "Content-Type",
										"name": "Content-Type",
										"value": "application/json",
										"type": "text"
									}
								],
								"body": {
									"mode": "raw",
									"raw": "{  \r\n  \"id\": \"{{$guid}}\",\r\n  \"method\": \"get\",\r\n  \"uri\": \"/threads/{{user-identity}}\"\r\n}"
								},
								"url": {
									"raw": "https://msging.net/commands",
									"protocol": "https",
									"host": [
										"msging",
										"net"
									],
									"path": [
										"commands"
									]
								}
							},
							"response": []
						}
					],
					"event": [
						{
							"listen": "prerequest",
							"script": {
								"id": "f52d12fc-e705-4360-98de-1dd089d4a7e0",
								"type": "text/javascript",
								"exec": [
									""
								]
							}
						},
						{
							"listen": "test",
							"script": {
								"id": "b9fc678d-a8a0-44fa-81e3-5299878dae33",
								"type": "text/javascript",
								"exec": [
									""
								]
							}
						}
					],
					"_postman_isSubFolder": true
				},
				{
					"name": "ChatbotProfile",
					"item": [
						{
							"name": "Set Greeting Message",
							"request": {
								"method": "POST",
								"header": [
									{
										"key": "Authorization",
										"type": "text",
										"value": "{{Authorization}}"
									},
									{
										"key": "Content-Type",
										"type": "text",
										"value": "application/json"
									}
								],
								"body": {
									"mode": "raw",
									"raw": "{  \r\n  \"id\": \"{{$guid}}\",\r\n  \"method\": \"set\",\r\n  \"uri\": \"/profile/greeting\",\r\n  \"type\": \"text/plain\",\r\n  \"resource\": \"Hello and welcome to our service!\"\r\n}"
								},
								"url": {
									"raw": "https://msging.net/commands",
									"protocol": "https",
									"host": [
										"msging",
										"net"
									],
									"path": [
										"commands"
									]
								}
							},
							"response": []
						},
						{
							"name": "Set Persistent Menu",
							"request": {
								"method": "POST",
								"header": [
									{
										"key": "Authorization",
										"type": "text",
										"value": "{{Authorization}}"
									},
									{
										"key": "Content-Type",
										"type": "text",
										"value": "application/json"
									}
								],
								"body": {
									"mode": "raw",
									"raw": "{  \r\n  \"id\": \"{{$guid}}\",\r\n  \"method\": \"set\",\r\n  \"uri\":\"/profile/persistent-menu\",\r\n  \"type\":\"application/vnd.lime.document-select+json\",\r\n  \"resource\": {\r\n    \"options\":[\r\n      {\r\n        \"label\":{\r\n          \"type\":\"text/plain\",\r\n          \"value\":\"Option 1\"\r\n        }\r\n      },\r\n      {\r\n        \"label\":{\r\n          \"type\":\"text/plain\",\r\n          \"value\":\"Option 2\"\r\n        }\r\n      },\r\n      {\r\n        \"label\":{\r\n          \"type\":\"text/plain\",\r\n          \"value\":\"Option 3\"\r\n        }\r\n      }\r\n    ]\r\n  }\r\n}\r\n"
								},
								"url": {
									"raw": "https://msging.net/commands",
									"protocol": "https",
									"host": [
										"msging",
										"net"
									],
									"path": [
										"commands"
									]
								}
							},
							"response": []
						},
						{
							"name": "Set Start Button",
							"request": {
								"method": "POST",
								"header": [
									{
										"key": "Authorization",
										"value": "{{Authorization}}",
										"type": "text"
									},
									{
										"key": "Content-Type",
										"name": "Content-Type",
										"value": "application/json",
										"type": "text"
									}
								],
								"body": {
									"mode": "raw",
									"raw": "{  \r\n  \"id\": \"{{$guid}}\",\r\n  \"method\": \"set\",\r\n  \"uri\": \"/profile/get-started\",\r\n  \"type\": \"text/plain\",\r\n  \"resource\": \"Start now\"\r\n}\r\n"
								},
								"url": {
									"raw": "https://msging.net/commands",
									"protocol": "https",
									"host": [
										"msging",
										"net"
									],
									"path": [
										"commands"
									]
								}
							},
							"response": []
						},
						{
							"name": "Get Greeting Message",
							"request": {
								"method": "POST",
								"header": [
									{
										"key": "Authorization",
										"value": "{{Authorization}}",
										"type": "text"
									},
									{
										"key": "Content-Type",
										"name": "Content-Type",
										"value": "application/json",
										"type": "text"
									}
								],
								"body": {
									"mode": "raw",
									"raw": "{  \r\n  \"id\": \"{{$guid}}\",\r\n  \"method\": \"get\",\r\n  \"uri\": \"/profile/greeting\"  \r\n}"
								},
								"url": {
									"raw": "https://msging.net/commands",
									"protocol": "https",
									"host": [
										"msging",
										"net"
									],
									"path": [
										"commands"
									]
								}
							},
							"response": []
						}
					],
					"_postman_isSubFolder": true
				},
				{
					"name": "Contacts",
					"item": [
						{
							"name": "Add/Update a Contact",
							"request": {
								"method": "POST",
								"header": [
									{
										"key": "Authorization",
										"value": "{{Authorization}}",
										"type": "text"
									},
									{
										"key": "Content-Type",
										"name": "Content-Type",
										"value": "application/json",
										"type": "text"
									}
								],
								"body": {
									"mode": "raw",
									"raw": "{  \r\n  \"id\": \"{{$guid}}\",\r\n  \"method\": \"set\",\r\n  \"uri\": \"/contacts\",\r\n  \"type\": \"application/vnd.lime.contact+json\",\r\n  \"resource\": {\r\n    \"identity\": \"11121023102013021@messenger.gw.msging.net\",\r\n    \"name\": \"John Doe\",\r\n    \"gender\":\"male\",\r\n    \"group\":\"friends\",    \r\n    \"extras\": {\r\n      \"plan\":\"Gold\",\r\n      \"code\":\"1111\"      \r\n    }\r\n  }\r\n}"
								},
								"url": {
									"raw": "https://msging.net/commands",
									"protocol": "https",
									"host": [
										"msging",
										"net"
									],
									"path": [
										"commands"
									]
								}
							},
							"response": []
						},
						{
							"name": "Get a Contact",
							"request": {
								"method": "POST",
								"header": [
									{
										"key": "Authorization",
										"value": "{{Authorization}}",
										"type": "text"
									},
									{
										"key": "Content-Type",
										"name": "Content-Type",
										"value": "application/json",
										"type": "text"
									}
								],
								"body": {
									"mode": "raw",
									"raw": "{  \r\n  \"id\": \"{{$guid}}\",\r\n  \"method\": \"get\",\r\n  \"uri\": \"/contacts/11121023102013021@messenger.gw.msging.net\"\r\n}"
								},
								"url": {
									"raw": "https://msging.net/commands",
									"protocol": "https",
									"host": [
										"msging",
										"net"
									],
									"path": [
										"commands"
									]
								}
							},
							"response": []
						},
						{
							"name": "Get all Contacts",
							"request": {
								"method": "POST",
								"header": [
									{
										"key": "Authorization",
										"value": "{{Authorization}}",
										"type": "text"
									},
									{
										"key": "Content-Type",
										"name": "Content-Type",
										"value": "application/json",
										"type": "text"
									}
								],
								"body": {
									"mode": "raw",
									"raw": "{  \r\n  \"id\": \"{{$guid}}\",\r\n  \"method\": \"get\",\r\n  \"uri\": \"/contacts?$skip=0&$take=3\"\r\n}"
								},
								"url": {
									"raw": "https://msging.net/commands",
									"protocol": "https",
									"host": [
										"msging",
										"net"
									],
									"path": [
										"commands"
									]
								}
							},
							"response": []
						}
					],
					"_postman_isSubFolder": true
				},
				{
					"name": "Context",
					"item": [
						{
							"name": "Set Builder's User State",
							"request": {
								"method": "POST",
								"header": [
									{
										"key": "Authorization",
										"value": "{{Authorization}}",
										"type": "text"
									},
									{
										"key": "Content-Type",
										"value": "application/json",
										"type": "text"
									}
								],
								"body": {
									"mode": "raw",
									"raw": "{\r\n  \"id\": \"12355433\",\r\n  \"to\": \"postmaster@msging.net\",\r\n  \"method\": \"set\",\r\n  \"uri\": \"/contexts/78b8d8c7-cf70-4b69-8fc5-1edd4a1d1fd5.pacheco%400mn.io/stateid%400\",\r\n  \"type\": \"text/plain\",\r\n  \"resource\": \"Test\"\r\n}"
								},
								"url": {
									"raw": "https://msging.net/commands",
									"protocol": "https",
									"host": [
										"msging",
										"net"
									],
									"path": [
										"commands"
									]
								}
							},
							"response": []
						},
						{
							"name": "Get Builder's User State",
							"request": {
								"method": "POST",
								"header": [
									{
										"key": "Authorization",
										"type": "text",
										"value": "{{Authorization}}"
									},
									{
										"key": "Content-Type",
										"type": "text",
										"value": "application/json"
									}
								],
								"body": {
									"mode": "raw",
									"raw": "{\r\n  \"id\": \"12355433\",\r\n  \"to\": \"postmaster@msging.net\",\r\n  \"method\": \"get\",\r\n  \"uri\": \"/contexts/78b8d8c7-cf70-4b69-8fc5-1edd4a1d1fd5.pacheco%400mn.io/stateid%400\"\r\n}"
								},
								"url": {
									"raw": "https://msging.net/commands",
									"protocol": "https",
									"host": [
										"msging",
										"net"
									],
									"path": [
										"commands"
									]
								}
							},
							"response": []
						}
					],
					"_postman_isSubFolder": true
				},
				{
					"name": "Delegation",
					"item": [
						{
							"name": "Grant Permissions",
							"request": {
								"method": "POST",
								"header": [
									{
										"key": "Authorization",
										"value": "{{Authorization}}",
										"type": "text"
									},
									{
										"key": "Content-Type",
										"name": "Content-Type",
										"value": "application/json",
										"type": "text"
									}
								],
								"body": {
									"mode": "raw",
									"raw": "{  \r\n  \"id\": \"{{$guid}}\",\r\n  \"method\": \"set\",\r\n  \"type\": \"application/vnd.lime.delegation+json\",\r\n  \"uri\": \"/delegations\",\r\n  \"resource\": {  \r\n    \"target\": \"postmaster@broadcast.msging.net\",\r\n    \"envelopeTypes\": [  \r\n      \"message\"\r\n    ]\r\n  }\r\n}"
								},
								"url": {
									"raw": "https://msging.net/commands",
									"protocol": "https",
									"host": [
										"msging",
										"net"
									],
									"path": [
										"commands"
									]
								}
							},
							"response": []
						},
						{
							"name": "Revoke Permissions",
							"request": {
								"method": "POST",
								"header": [
									{
										"key": "Authorization",
										"value": "{{Authorization}}",
										"type": "text"
									},
									{
										"key": "Content-Type",
										"name": "Content-Type",
										"value": "application/json",
										"type": "text"
									}
								],
								"body": {
									"mode": "raw",
									"raw": "{  \r\n  \"id\": \"{{$guid}}\",\r\n  \"method\": \"delete\",\r\n  \"uri\": \"/delegations/postmaster@broadcast.msging.net?envelopeTypes=message\"\r\n}"
								},
								"url": {
									"raw": "https://msging.net/commands",
									"protocol": "https",
									"host": [
										"msging",
										"net"
									],
									"path": [
										"commands"
									]
								}
							},
							"response": []
						}
					],
					"_postman_isSubFolder": true
				},
				{
					"name": "Desk",
					"item": [
						{
							"name": "Open a Ticket",
							"request": {
								"method": "POST",
								"header": [
									{
										"key": "Authorization",
										"value": "{{Authorization}}"
									},
									{
										"key": "Content-Type",
										"value": "application/json"
									}
								],
								"body": {
									"mode": "raw",
									"raw": "{\r\n  \"id\": \"{{$guid}}\",\r\n  \"to\": \"postmaster@desk.msging.net\",\r\n  \"method\": \"set\",\r\n  \"uri\": \"/tickets/{{user-identity}}\",\r\n  \"type\": \"text/plain\",\r\n  \"resource\": \"I need a human!\"\r\n}"
								},
								"url": {
									"raw": "https://msging.net/commands",
									"protocol": "https",
									"host": [
										"msging",
										"net"
									],
									"path": [
										"commands"
									]
								}
							},
							"response": []
						},
						{
							"name": "Get all Ticket",
							"request": {
								"method": "POST",
								"header": [
									{
										"key": "Authorization",
										"value": "{{Authorization}}"
									},
									{
										"key": "Content-Type",
										"value": "application/json"
									}
								],
								"body": {
									"mode": "raw",
									"raw": "{\r\n  \"id\": \"{{$guid}}\",\r\n  \"to\": \"postmaster@desk.msging.net\",\r\n  \"method\": \"get\",\r\n  \"uri\": \"/tickets?$take=10\"\r\n}"
								},
								"url": {
									"raw": "https://msging.net/commands",
									"protocol": "https",
									"host": [
										"msging",
										"net"
									],
									"path": [
										"commands"
									]
								}
							},
							"response": []
						},
						{
							"name": "Close a Ticket as an User",
							"request": {
								"method": "POST",
								"header": [
									{
										"key": "Authorization",
										"value": "{{Authorization}}"
									},
									{
										"key": "Content-Type",
										"value": "application/json"
									}
								],
								"body": {
									"mode": "raw",
									"raw": "{\r\n  \"id\": \"{{$guid}}\",\r\n  \"to\": \"postmaster@desk.msging.net\",\r\n  \"method\": \"set\",\r\n  \"uri\": \"/tickets/change-status\",\r\n  \"type\": \"application/vnd.iris.ticket+json\",\r\n  \"resource\": {\r\n    \"id\": \"{{ticket-id}}\",\r\n    \"status\": \"ClosedClient\"\r\n  }\r\n}"
								},
								"url": {
									"raw": "https://msging.net/commands",
									"protocol": "https",
									"host": [
										"msging",
										"net"
									],
									"path": [
										"commands"
									]
								}
							},
							"response": []
						},
						{
							"name": "Change a Ticket Status",
							"request": {
								"method": "POST",
								"header": [
									{
										"key": "Authorization",
										"value": "{{Authorization}}"
									},
									{
										"key": "Content-Type",
										"value": "application/json"
									}
								],
								"body": {
									"mode": "raw",
									"raw": "{\r\n  \"id\": \"{{$guid}}\",\r\n  \"to\": \"postmaster@desk.msging.net\",\r\n  \"method\": \"set\",\r\n  \"uri\": \"/tickets/change-status\",\r\n  \"type\": \"application/vnd.iris.ticket+json\",\r\n  \"resource\": {\r\n  \t\"id\": \"{{ticket-id}}\",\r\n  \t\"status\": \"ClosedClient\"\r\n  }\r\n}"
								},
								"url": {
									"raw": "https://msging.net/commands",
									"protocol": "https",
									"host": [
										"msging",
										"net"
									],
									"path": [
										"commands"
									]
								}
							},
							"response": []
						},
						{
							"name": "Finishing a ticket",
							"request": {
								"method": "POST",
								"header": [
									{
										"key": "Authorization",
										"value": "{{Authorization}}"
									},
									{
										"key": "Content-Type",
										"value": "application/json"
									}
								],
								"body": {
									"mode": "raw",
									"raw": "{\r\n  \"id\": \"xulambis\",\r\n  \"to\": \"postmaster@desk.msging.net\",\r\n  \"method\": \"set\",\r\n  \"uri\": \"/tickets/f1e95e10-2e21-4438-a076-71183b253981/close\"\r\n}"
								},
								"url": {
									"raw": "https://msging.net/commands",
									"protocol": "https",
									"host": [
										"msging",
										"net"
									],
									"path": [
										"commands"
									]
								}
							},
							"response": []
						},
						{
							"name": "Get all Attendants",
							"request": {
								"method": "POST",
								"header": [
									{
										"key": "Authorization",
										"value": "{{Authorization}}"
									},
									{
										"key": "Content-Type",
										"value": "application/json"
									}
								],
								"body": {
									"mode": "raw",
									"raw": "{\r\n  \"id\": \"{{$guid}}\",\r\n  \"to\": \"postmaster@desk.msging.net\",\r\n  \"method\": \"get\",\r\n  \"uri\": \"/attendants\"\r\n}"
								},
								"url": {
									"raw": "https://msging.net/commands",
									"protocol": "https",
									"host": [
										"msging",
										"net"
									],
									"path": [
										"commands"
									]
								}
							},
							"response": []
						},
						{
							"name": "Transfer a Ticket",
							"request": {
								"method": "POST",
								"header": [
									{
										"key": "Authorization",
										"value": "{{Authorization}}"
									},
									{
										"key": "Content-Type",
										"value": "application/json"
									}
								],
								"body": {
									"mode": "raw",
									"raw": "{ \r\n  \"id\": \"{{$guid}}\",\r\n  \"method\": \"set\",\r\n  \"uri\": \"/tickets/{{ticket-id}}/transfer\",\r\n  \"to\": \"postmaster@desk.msging.net\",\r\n  \"type\": \"application/vnd.iris.ticket+json\",\r\n  \"resource\": {\r\n  \t\"team\": \"Default\"\r\n  }\r\n}"
								},
								"url": {
									"raw": "https://msging.net/commands",
									"protocol": "https",
									"host": [
										"msging",
										"net"
									],
									"path": [
										"commands"
									]
								}
							},
							"response": []
						}
					],
					"description": "Requests available for BLiP Desk extension",
					"_postman_isSubFolder": true
				},
				{
					"name": "EventAnalysis",
					"item": [
						{
							"name": "Create an Event",
							"request": {
								"method": "POST",
								"header": [
									{
										"key": "Authorization",
										"value": "{{Authorization}}",
										"type": "text"
									},
									{
										"key": "Content-Type",
										"name": "Content-Type",
										"value": "application/json",
										"type": "text"
									}
								],
								"body": {
									"mode": "raw",
									"raw": "{\r\n  \"id\": \"{{$guid}}\",\r\n  \"to\": \"postmaster@analytics.msging.net\",\r\n  \"method\": \"set\",\r\n  \"type\": \"application/vnd.iris.eventTrack+json\",\r\n  \"uri\": \"/event-track\",\r\n  \"resource\": {\r\n    \"category\": \"payments\",\r\n    \"action\": \"success-order\"\r\n  }\r\n}"
								},
								"url": {
									"raw": "https://msging.net/commands",
									"protocol": "https",
									"host": [
										"msging",
										"net"
									],
									"path": [
										"commands"
									]
								}
							},
							"response": []
						},
						{
							"name": "Get Categories",
							"request": {
								"method": "POST",
								"header": [
									{
										"key": "Authorization",
										"value": "{{Authorization}}",
										"type": "text"
									},
									{
										"key": "Content-Type",
										"name": "Content-Type",
										"value": "application/json",
										"type": "text"
									}
								],
								"body": {
									"mode": "raw",
									"raw": "{\r\n  \"id\": \"{{$guid}}\",\r\n  \"to\": \"postmaster@analytics.msging.net\",\r\n  \"method\": \"get\",\r\n  \"uri\": \"/event-track\"\r\n}"
								},
								"url": {
									"raw": "https://msging.net/commands",
									"protocol": "https",
									"host": [
										"msging",
										"net"
									],
									"path": [
										"commands"
									]
								}
							},
							"response": []
						},
						{
							"name": "Get Counters",
							"request": {
								"method": "POST",
								"header": [
									{
										"key": "Authorization",
										"type": "text",
										"value": "{{Authorization}}"
									},
									{
										"key": "Content-Type",
										"name": "Content-Type",
										"type": "text",
										"value": "application/json"
									}
								],
								"body": {
									"mode": "raw",
									"raw": "{\r\n  \"id\": \"{{$guid}}\",\r\n  \"to\": \"postmaster@analytics.msging.net\",\r\n  \"method\": \"get\",\r\n  \"uri\": \"/event-track/payments?startDate=2016-01-01&$take=10\"\r\n}"
								},
								"url": {
									"raw": "https://msging.net/commands",
									"protocol": "https",
									"host": [
										"msging",
										"net"
									],
									"path": [
										"commands"
									]
								}
							},
							"response": []
						},
						{
							"name": "Get Events Details",
							"request": {
								"method": "POST",
								"header": [
									{
										"key": "Authorization",
										"type": "text",
										"value": "{{Authorization}}"
									},
									{
										"key": "Content-Type",
										"name": "Content-Type",
										"type": "text",
										"value": "application/json"
									}
								],
								"body": {
									"mode": "raw",
									"raw": "{\r\n  \"id\": \"{{$guid}}\",\r\n  \"to\": \"postmaster@analytics.msging.net\",\r\n  \"method\": \"get\",\r\n  \"uri\": \"/event-track/payments/success-order?startDate=2016-01-01&$take=10\"\r\n}"
								},
								"url": {
									"raw": "https://msging.net/commands",
									"protocol": "https",
									"host": [
										"msging",
										"net"
									],
									"path": [
										"commands"
									]
								}
							},
							"response": []
						}
					],
					"_postman_isSubFolder": true
				},
				{
					"name": "Resources",
					"item": [
						{
							"name": "Store a resource",
							"request": {
								"method": "POST",
								"header": [
									{
										"key": "Authorization",
										"type": "text",
										"value": "{{Authorization}}"
									},
									{
										"key": "Content-Type",
										"name": "Content-Type",
										"type": "text",
										"value": "application/json"
									}
								],
								"body": {
									"mode": "raw",
									"raw": "{  \r\n  \"id\": \"{{$guid}}\",\r\n  \"method\": \"set\",\r\n  \"uri\": \"/resources/xyz1234\",\r\n  \"type\": \"application/vnd.lime.media-link+json\",\r\n  \"resource\": {\r\n    \"title\": \"Cat\",\r\n    \"text\": \"Here is a cat image for you!\",\r\n    \"type\": \"image/jpeg\",\r\n    \"uri\": \"http://2.bp.blogspot.com/-pATX0YgNSFs/VP-82AQKcuI/AAAAAAAALSU/Vet9e7Qsjjw/s1600/Cat-hd-wallpapers.jpg\",\r\n    \"size\": 227791,\r\n    \"previewUri\": \"https://encrypted-tbn3.gstatic.com/images?q=tbn:ANd9GcS8qkelB28RstsNxLi7gbrwCLsBVmobPjb5IrwKJSuqSnGX4IzX\",\r\n    \"previewType\": \"image/jpeg\"\r\n  }\r\n}"
								},
								"url": {
									"raw": "https://msging.net/commands",
									"protocol": "https",
									"host": [
										"msging",
										"net"
									],
									"path": [
										"commands"
									]
								}
							},
							"response": []
						}
					],
					"_postman_isSubFolder": true
				},
				{
					"name": "Tunnel",
					"item": [
						{
							"name": "Get Tunnel Informations",
							"request": {
								"method": "POST",
								"header": [
									{
										"key": "Authorization",
										"type": "text",
										"value": "{{Authorization}}"
									},
									{
										"key": "Content-Type",
										"name": "Content-Type",
										"type": "text",
										"value": "application/json"
									}
								],
								"body": {
									"mode": "raw",
									"raw": "{\r\n    \"id\": \"{{$guid}}\",\r\n    \"from\": \"operator@msging.net/instance\",\r\n    \"to\": \"postmaster@tunnel.msging.net\",\r\n    \"method\":\"get\",\r\n    \"uri\": \"lime://tunnel.msging.net/accounts/{{tunnel-id}}\"\r\n}"
								},
								"url": {
									"raw": "https://msging.net/commands",
									"protocol": "https",
									"host": [
										"msging",
										"net"
									],
									"path": [
										"commands"
									]
								}
							},
							"response": []
						}
					],
					"_postman_isSubFolder": true
				},
				{
					"name": "UserInfo",
					"item": [
						{
							"name": "Get info about a Messenger client",
							"request": {
								"method": "POST",
								"header": [
									{
										"key": "Authorization",
										"type": "text",
										"value": "{{Authorization}}"
									},
									{
										"key": "Content-Type",
										"type": "text",
										"value": "application/json"
									}
								],
								"body": {
									"mode": "raw",
									"raw": "{  \r\n  \"id\": \"{{$guid}}\",\r\n  \"to\": \"postmaster@messenger.gw.msging.net\",\r\n  \"method\": \"get\",\r\n  \"uri\": \"lime://messenger.gw.msging.net/accounts/{{user-idenitity}}\"\r\n}"
								},
								"url": {
									"raw": "https://msging.net/commands",
									"protocol": "https",
									"host": [
										"msging",
										"net"
									],
									"path": [
										"commands"
									]
								}
							},
							"response": []
						},
						{
							"name": "Get info about a Telegram client",
							"request": {
								"method": "POST",
								"header": [
									{
										"key": "Authorization",
										"type": "text",
										"value": "{{Authorization}}"
									},
									{
										"key": "Content-Type",
										"type": "text",
										"value": "application/json"
									}
								],
								"body": {
									"mode": "raw",
									"raw": "{  \r\n  \"id\": \"{{$guid}}\",\r\n  \"to\": \"postmaster@messenger.gw.msging.net\",\r\n  \"method\": \"get\",\r\n  \"uri\": \"lime://telegram.gw.msging.net/accounts/{{user-identity}}\"\r\n}"
								},
								"url": {
									"raw": "https://msging.net/commands",
									"protocol": "https",
									"host": [
										"msging",
										"net"
									],
									"path": [
										"commands"
									]
								}
							},
							"response": []
						}
					],
					"_postman_isSubFolder": true
				},
				{
					"name": "Schedule",
					"item": [
						{
							"name": "Create a scheduling",
							"request": {
								"method": "POST",
								"header": [
									{
										"key": "Authorization",
										"type": "text",
										"value": "{{Authorization}}"
									},
									{
										"key": "Content-Type",
										"name": "Content-Type",
										"type": "text",
										"value": "application/json"
									}
								],
								"body": {
									"mode": "raw",
									"raw": "{  \r\n  \"id\": \"{{$guid}}\",\r\n  \"to\": \"postmaster@scheduler.msging.net\",\r\n  \"method\": \"set\",\r\n  \"uri\": \"/schedules\",\r\n  \"type\": \"application/vnd.iris.schedule+json\",\r\n  \"resource\": {  \r\n    \"message\": {  \r\n      \"id\": \"ad19adf8-f5ec-4fff-8aeb-2e7ebe9f7a67\",\r\n      \"to\": \"destination@0mn.io\",\r\n      \"type\": \"text/plain\",\r\n      \"content\": \"Scheduling test\"\r\n    },\r\n    \"when\": \"2016-07-25T17:50:00.000Z\"\r\n  }\r\n}"
								},
								"url": {
									"raw": "https://msging.net/commands",
									"protocol": "https",
									"host": [
										"msging",
										"net"
									],
									"path": [
										"commands"
									]
								}
							},
							"response": []
						},
						{
							"name": "Get a Scheduled Message",
							"request": {
								"method": "POST",
								"header": [
									{
										"key": "Authorization",
										"type": "text",
										"value": "{{Authorization}}"
									},
									{
										"key": "Content-Type",
										"name": "Content-Type",
										"type": "text",
										"value": "application/json"
									}
								],
								"body": {
									"mode": "raw",
									"raw": "{  \r\n  \"id\": \"{{$guid}}\",\r\n  \"to\": \"postmaster@scheduler.msging.net\",\r\n  \"method\": \"get\",\r\n  \"uri\": \"/schedules/{{scheduled-message-id}}\"\r\n}"
								},
								"url": {
									"raw": "https://msging.net/commands",
									"protocol": "https",
									"host": [
										"msging",
										"net"
									],
									"path": [
										"commands"
									]
								}
							},
							"response": []
						}
					],
					"event": [
						{
							"listen": "prerequest",
							"script": {
								"id": "9fa519f1-8857-4785-bff1-3a326b4d0da8",
								"type": "text/javascript",
								"exec": [
									""
								]
							}
						},
						{
							"listen": "test",
							"script": {
								"id": "f4594946-6d87-4ce8-82df-e613408c877b",
								"type": "text/javascript",
								"exec": [
									""
								]
							}
						}
					],
					"_postman_isSubFolder": true
				}
			],
			"description": "Requests for any BLiP's extension",
			"event": [
				{
					"listen": "prerequest",
					"script": {
						"id": "6ebd3e6a-cbd8-4b33-8b18-d9b48c8aaa75",
						"type": "text/javascript",
						"exec": [
							""
						]
					}
				},
				{
					"listen": "test",
					"script": {
						"id": "a3077574-7e84-4d1a-8823-87308ba4f611",
						"type": "text/javascript",
						"exec": [
							""
						]
					}
				}
			]
		},
		{
			"name": "Integrations",
			"item": [
				{
					"name": "WhatsApp",
					"item": [
						{
							"name": "Verify Whatsapp Identifier",
							"request": {
								"method": "POST",
								"header": [
									{
										"key": "Authorization",
										"value": "{{Authorization}}"
									},
									{
										"key": "Content-Type",
										"value": "application/json"
									}
								],
								"body": {
									"mode": "raw",
									"raw": "{  \r\n  \"id\": \"a456-42665544000-0123e4567-e89b-12d3\",\r\n  \"to\": \"postmaster@wa.gw.msging.net\",\r\n  \"method\": \"get\",\r\n  \"uri\": \"lime://wa.gw.msging.net/accounts/+5531986055572\"\r\n}"
								},
								"url": {
									"raw": "https://msging.net/commands",
									"protocol": "https",
									"host": [
										"msging",
										"net"
									],
									"path": [
										"commands"
									]
								},
								"description": "Use this request to verify what is the Whatsapp identifier associated with a phone number."
							},
							"response": []
						},
						{
							"name": "Send a Message",
							"request": {
								"method": "POST",
								"header": [
									{
										"key": "Authorization",
										"value": "{{Authorization}}"
									},
									{
										"key": "Content-Type",
										"value": "application/json"
									}
								],
								"body": {
									"mode": "raw",
									"raw": "{\r\n  \"id\": \"123e4567-e89b-12d3-a456-426655440002\",\r\n  \"to\": \"553198271039@wa.gw.msging.net\",\r\n  \"type\": \"application/json\",\r\n  \"content\": {\r\n    \"type\": \"hsm\",\r\n    \"hsm\": {\r\n      \"namespace\": \"whatsapp:hsm:messaging:blip\",\r\n      \"element_name\": \"account_created\",\r\n      \"fallback_lg\": \"pt\",\r\n      \"fallback_lc\": \"BR\",\r\n      \"localizable_params\": [\r\n        {\r\n          \"default\": \"BLiPPer\"\r\n        }\r\n      ]\r\n    }\r\n  }\r\n}\r\n"
								},
								"url": {
									"raw": "https://msging.net/messages",
									"protocol": "https",
									"host": [
										"msging",
										"net"
									],
									"path": [
										"messages"
									]
								},
								"description": "Send a message to a Whatsapp user"
							},
							"response": []
						}
					],
					"_postman_isSubFolder": true
				},
				{
					"name": "Skype",
					"item": [
						{
							"name": "GetTokenOauth",
							"request": {
								"method": "GET",
								"header": [],
								"body": {
									"mode": "raw",
									"raw": ""
								},
								"url": {
									"raw": ""
								}
							},
							"response": []
						},
						{
							"name": "SendText",
							"request": {
								"method": "GET",
								"header": [],
								"body": {
									"mode": "raw",
									"raw": ""
								},
								"url": {
									"raw": ""
								}
							},
							"response": []
						}
					],
					"_postman_isSubFolder": true
				},
				{
					"name": "Tangram",
					"item": [
						{
							"name": "Send Message",
							"request": {
								"method": "POST",
								"header": [
									{
										"key": "Authorization",
										"value": "{{Authorization}}",
										"type": "text"
									},
									{
										"key": "Content-Type",
										"value": "application/json",
										"type": "text"
									}
								],
								"body": {
									"mode": "raw",
									"raw": "{\r\n    \"id\": \"batata\",\r\n    \"to\": \"5531998271039@tangram.com.br\",\r\n    \"type\": \"text/plain\",\r\n    \"content\": \"Do you beleive or not?\"\r\n}"
								},
								"url": {
									"raw": "https://msging.net/messages",
									"protocol": "https",
									"host": [
										"msging",
										"net"
									],
									"path": [
										"messages"
									]
								},
								"description": "Sends a SMS message to a client"
							},
							"response": []
						}
					],
					"_postman_isSubFolder": true
				},
				{
					"name": "Infobip",
					"item": [
						{
							"name": "Send Message",
							"request": {
								"method": "POST",
								"header": [
									{
										"key": "Authorization",
										"value": "{{Authorization}}",
										"type": "text"
									},
									{
										"key": "Content-Type",
										"value": "application/json",
										"type": "text"
									}
								],
								"body": {
									"mode": "raw",
									"raw": "{\r\n    \"id\": \"teste1-info\",\r\n    \"to\": \"31998271039@infobip.gw.msging.net\",\r\n    \"type\": \"text/plain\",\r\n    \"content\": \"Do you beleive or not?\"\r\n}"
								},
								"url": {
									"raw": "https://msging.net/messages",
									"protocol": "https",
									"host": [
										"msging",
										"net"
									],
									"path": [
										"messages"
									]
								},
								"description": "Sends a SMS message to a client"
							},
							"response": []
						}
					],
					"_postman_isSubFolder": true
				}
			],
			"description": "All requests for any BLiP's extension"
		},
		{
			"name": "Send a Command",
			"request": {
				"method": "POST",
				"header": [
					{
						"key": "Authorization",
						"value": "{{Authorization}}"
					},
					{
						"key": "Content-Type",
						"value": "application/json"
					}
				],
				"body": {
					"mode": "raw",
					"raw": "{\r\n  \"id\": \"{{$guid}}\",\r\n  \"to\": \"postmaster@analytics.msging.net\",\r\n  \"method\": \"set\",\r\n  \"type\": \"application/vnd.iris.eventTrack+json\",\r\n  \"uri\": \"/event-track\",\r\n  \"resource\": {\r\n    \"category\": \"payments\",\r\n    \"action\": \"success-order\"\r\n  }\r\n}"
				},
				"url": {
					"raw": "https://msging.net/commands",
					"protocol": "https",
					"host": [
						"msging",
						"net"
					],
					"path": [
						"commands"
					]
				}
			},
			"response": []
		},
		{
			"name": "Send a Message",
			"request": {
				"method": "POST",
				"header": [
					{
						"key": "Authorization",
						"value": "{{Authorization}}"
					},
					{
						"key": "Content-Type",
						"value": "application/json"
					}
				],
				"body": {
					"mode": "raw",
					"raw": "{\r\n  \"id\": \"{{$guid}}\",\r\n  \"to\": \"{{user-identity}}\",\r\n  \"type\": \"text/plain\",\r\n  \"content\": \"Hello, how can I help you?\"\r\n}"
				},
				"url": {
					"raw": "https://msging.net/messages",
					"protocol": "https",
					"host": [
						"msging",
						"net"
					],
					"path": [
						"messages"
					]
				}
			},
			"response": []
		},
		{
			"name": "Send a Notification",
			"request": {
				"method": "POST",
				"header": [
					{
						"key": "Authorization",
						"value": "{{Authorization}}"
					},
					{
						"key": "Content-Type",
						"value": "application/json"
					}
				],
				"body": {
					"mode": "raw",
					"raw": "{\r\n  \"id\": \"{{message-id}}\",\r\n  \"to\": \"{{user-identity}}\",\r\n  \"event\": \"received\"\r\n}"
				},
				"url": {
					"raw": "https://msging.net/notifications",
					"protocol": "https",
					"host": [
						"msging",
						"net"
					],
					"path": [
						"notifications"
					]
				}
			},
			"response": []
		}
	],
	"event": [
		{
			"listen": "prerequest",
			"script": {
				"id": "48ac605f-de8a-403e-ab6e-3e66bfec3005",
				"type": "text/javascript",
				"exec": [
					""
				]
			}
		},
		{
			"listen": "test",
			"script": {
				"id": "458abdef-b959-42ab-b1da-a4b644a0b072",
				"type": "text/javascript",
				"exec": [
					""
				]
			}
		}
	],
	"variable": [
		{
			"id": "cce16fc8-3117-45a1-9b8e-1769e6f8245b",
			"key": "Authorization",
			"value": "<your-chatbot-api-key>",
			"type": "string"
		}
	]
}